{
  "schema": "atlas.snapshot.v7",
  "version": "7.3.0-public",
  "generatedAt": "2026-07-16T11:43:09.794Z",
  "snapshot": {
    "memoryEngineSchema": "public-curated-snapshot.v1",
    "memoryFiles": 6,
    "graphJsonUsedAsNodeEdgeSource": false,
    "activeMarkdownCount": 6,
    "archiveMarkdownCount": 0,
    "buildState": "public_curated_snapshot"
  },
  "proofBoundary": {
    "atlas": "team-readable public snapshot",
    "canonical": "not included in public bundle",
    "actualObsidianGraphView": "not included",
    "notionVisualQa": "not included"
  },
  "workspaces": [
    "home",
    "explore",
    "observe",
    "flow",
    "time",
    "agency"
  ],
  "defaultFocus": "doc:pub:d2edeb88f1fb207d2e"
}
