{
  "districtOrder": [
    "중심 지식",
    "연구 논거",
    "전략",
    "운영 기반",
    "신호",
    "연구 기록",
    "Independent Projects"
  ],
  "matrix": [
    {
      "id": "pair:%EC%A4%91%EC%8B%AC%20%EC%A7%80%EC%8B%9D:%EC%97%B0%EA%B5%AC%20%EB%85%BC%EA%B1%B0",
      "source": "중심 지식",
      "target": "연구 논거",
      "wikilink": 395,
      "wikilinkForward": 8,
      "wikilinkReverse": 387,
      "typed": 0,
      "typedForward": 0,
      "typedReverse": 0,
      "route": 0,
      "total": 395
    },
    {
      "id": "pair:%EC%A4%91%EC%8B%AC%20%EC%A7%80%EC%8B%9D:%EC%A0%84%EB%9E%B5",
      "source": "중심 지식",
      "target": "전략",
      "wikilink": 1136,
      "wikilinkForward": 379,
      "wikilinkReverse": 757,
      "typed": 0,
      "typedForward": 0,
      "typedReverse": 0,
      "route": 0,
      "total": 1136
    },
    {
      "id": "pair:%EC%A4%91%EC%8B%AC%20%EC%A7%80%EC%8B%9D:%EC%8B%A0%ED%98%B8",
      "source": "중심 지식",
      "target": "신호",
      "wikilink": 672,
      "wikilinkForward": 152,
      "wikilinkReverse": 520,
      "typed": 0,
      "typedForward": 0,
      "typedReverse": 0,
      "route": 0,
      "total": 672
    },
    {
      "id": "pair:%EC%97%B0%EA%B5%AC%20%EB%85%BC%EA%B1%B0:%EC%A0%84%EB%9E%B5",
      "source": "연구 논거",
      "target": "전략",
      "wikilink": 57,
      "wikilinkForward": 53,
      "wikilinkReverse": 4,
      "typed": 0,
      "typedForward": 0,
      "typedReverse": 0,
      "route": 0,
      "total": 57
    },
    {
      "id": "pair:%EC%97%B0%EA%B5%AC%20%EB%85%BC%EA%B1%B0:%EC%8B%A0%ED%98%B8",
      "source": "연구 논거",
      "target": "신호",
      "wikilink": 8,
      "wikilinkForward": 7,
      "wikilinkReverse": 1,
      "typed": 0,
      "typedForward": 0,
      "typedReverse": 0,
      "route": 0,
      "total": 8
    },
    {
      "id": "pair:%EC%A0%84%EB%9E%B5:%EC%8B%A0%ED%98%B8",
      "source": "전략",
      "target": "신호",
      "wikilink": 141,
      "wikilinkForward": 67,
      "wikilinkReverse": 74,
      "typed": 0,
      "typedForward": 0,
      "typedReverse": 0,
      "route": 0,
      "total": 141
    }
  ],
  "typedRelations": [],
  "routeCoMembership": [],
  "neighborhoods": {},
  "layerDefinitions": [
    {
      "id": "wikilink",
      "label": "링크 출현 횟수",
      "meaning": "fresh release capture에서 유일하게 해결된 Markdown wikilink occurrence. 고유 문서쌍과 구분한다.",
      "unit": "resolved_link_occurrence"
    },
    {
      "id": "typed",
      "label": "명시 관계",
      "meaning": "공개 승인된 명시 관계",
      "unit": "typed_relation"
    },
    {
      "id": "route",
      "label": "작업 경로 렌즈",
      "meaning": "공개 승인된 경로 공동 소속",
      "unit": "curated_cross_district_route_pair"
    }
  ],
  "availableLayers": [
    "wikilink"
  ],
  "redactedLayers": [
    "typed",
    "route"
  ],
  "coverage": {
    "resolvedLinkPairs": 6,
    "resolvedLinkWeight": 8248,
    "unresolvedLinks": {},
    "unresolvedLinkTotal": 0,
    "ambiguousLinks": 0,
    "typedRelations": 0,
    "layers": {
      "wikilink": {
        "unit": "resolved_link_occurrence",
        "total": 8248,
        "interDistrict": 2409,
        "intraDistrict": 5839,
        "displayed": 2409,
        "reconciled": true,
        "boundary": "fresh capture에서 유일하게 해결된 represented hub 사이의 wikilink occurrence 집계"
      },
      "typed": {
        "unit": "typed_relation",
        "total": 0,
        "interDistrict": 0,
        "intraDistrict": 0,
        "displayed": 0,
        "reconciled": true,
        "boundary": "내부 방향성 관계 증거는 공개판에서 제외"
      },
      "route": {
        "unit": "curated_cross_district_route_pair",
        "total": 0,
        "interDistrict": 0,
        "intraDistrict": 0,
        "displayed": 0,
        "reconciled": true,
        "boundary": "내부 route membership은 공개판에서 제외"
      }
    },
    "boundary": "공개판은 represented hub 사이에서 유일하게 해결된 fresh wikilink만 구역 단위로 보여주며 미해결 후보는 투영 전에 제외한다."
  }
}
